<?xml version="1.0"?>
<variant name="Beelzebub">
<!--  Beelzebub - a variant by Chris Byler and Jay Delanoy -->
<!--  -->
    <creatures filename="BeelzebubCre.xml" />
    <strategic_map filename="BeelzebubMap.xml" />
    <terrain_recruits filename="BeelzebubTer.xml" />
    <hint classname="Beelzebub.BeelzebubHint" />
    <depends>
        <!-- make sure we pick stuff in Default instead of Undead -->
        <depend variant="Default" />
        <!-- for the Ruins Battlelands only -->
        <depend variant="Undead" />
    </depends>
</variant>
