<?xml version="1.0"?>
<battlemap terrain="Tower" tower="True">
<!--  Battlelands generated by BattlelandsBuilder -->
    <battlehex x="1" y="2" terrain="Tower" elevation="1">
        <border number="0" type="w" />
        <border number="3" type="w" />
        <border number="4" type="w" />
        <border number="5" type="w" />
    </battlehex>
    <battlehex x="2" y="2" terrain="Tower" elevation="2">
        <border number="0" type="c" />
        <border number="1" type="c" />
        <border number="2" type="w" />
        <border number="3" type="w" />
        <border number="4" type="w" />
        <border number="5" type="c" />
    </battlehex>
    <battlehex x="2" y="3" terrain="Tower" elevation="1">
        <border number="3" type="w" />
        <border number="4" type="w" />
    </battlehex>
    <battlehex x="3" y="2" terrain="Tower" elevation="1">
        <border number="0" type="w" />
        <border number="1" type="w" />
    </battlehex>
    <battlehex x="3" y="3" terrain="Tower" elevation="1">
        <border number="3" type="w" />
        <border number="4" type="w" />
    </battlehex>
    <battlehex x="4" y="3" terrain="Tower" elevation="2">
        <border number="0" type="c" />
        <border number="1" type="c" />
        <border number="2" type="c" />
        <border number="3" type="w" />
        <border number="4" type="w" />
        <border number="5" type="w" />
    </battlehex>
    <battlehex x="4" y="4" terrain="Tower" elevation="1">
        <border number="1" type="w" />
        <border number="2" type="w" />
        <border number="3" type="w" />
        <border number="4" type="w" />
    </battlehex>
    <startlist>
        <battlehexref label="C4" />
        <battlehexref label="E3" />
        <battlehexref label="D4" />
        <battlehexref label="B3" />
        <battlehexref label="C3" />
        <battlehexref label="D3" />
        <battlehexref label="E2" />
    </startlist>
</battlemap>
